MANIFEST.in
README.rst
setup.py
docs/COPYRIGHT.txt
docs/HISTORY.rst
docs/LICENSE.txt
src/http_session_file/__init__.py
src/http_session_file/store.py
src/http_session_file.egg-info/PKG-INFO
src/http_session_file.egg-info/SOURCES.txt
src/http_session_file.egg-info/dependency_links.txt
src/http_session_file.egg-info/not-zip-safe
src/http_session_file.egg-info/requires.txt
src/http_session_file.egg-info/top_level.txt
tests/test_session.py